sdflexutils/__init__.py
sdflexutils/client.py
sdflexutils/exception.py
sdflexutils/log.py
sdflexutils/utils.py
sdflexutils/common/__init__.py
sdflexutils/common/constants.py
sdflexutils/common/manager_utils.py
sdflexutils/common/raid_config_schema.json
sdflexutils/hpssa/__init__.py
sdflexutils/hpssa/disk_allocator.py
sdflexutils/hpssa/manager.py
sdflexutils/hpssa/objects.py
sdflexutils/ipa_hw_manager/__init__.py
sdflexutils/ipa_hw_manager/hardware_manager.py
sdflexutils/redfish/__init__.py
sdflexutils/redfish/common.py
sdflexutils/redfish/main.py
sdflexutils/redfish/redfish.py
sdflexutils/redfish/utils.py
sdflexutils/redfish/resources/__init__.py
sdflexutils/redfish/resources/update_service.py
sdflexutils/redfish/resources/system/__init__.py
sdflexutils/redfish/resources/system/constants.py
sdflexutils/redfish/resources/system/httpbooturi.py
sdflexutils/redfish/resources/system/mappings.py
sdflexutils/redfish/resources/system/secure_boot.py
sdflexutils/redfish/resources/system/system.py
sdflexutils/redfish/resources/system/virtual_media.py
sdflexutils/storcli/__init__.py
sdflexutils/storcli/disk_allocator.py
sdflexutils/storcli/manager.py
sdflexutils/storcli/storcli.py
sdflexutils/sum/__init__.py
sdflexutils/sum/sum_controller.py
sdflexutils/tests/__init__.py
sdflexutils/tests/base.py
sdflexutils/tests/unit/__init__.py
sdflexutils/tests/unit/test_client.py
sdflexutils/tests/unit/test_exception.py
sdflexutils/tests/unit/test_log.py
sdflexutils/tests/unit/test_utils.py
sdflexutils/tests/unit/common/__init__.py
sdflexutils/tests/unit/common/test_manager_utils.py
sdflexutils/tests/unit/hpssa/__init__.py
sdflexutils/tests/unit/hpssa/raid_constants.py
sdflexutils/tests/unit/hpssa/test_disk_allocator.py
sdflexutils/tests/unit/hpssa/test_manager.py
sdflexutils/tests/unit/hpssa/test_objects.py
sdflexutils/tests/unit/ipa_hw_manager/__init__.py
sdflexutils/tests/unit/ipa_hw_manager/test_hardware_manager.py
sdflexutils/tests/unit/redfish/__init__.py
sdflexutils-1.5.1.dist-info/AUTHORS
sdflexutils-1.5.1.dist-info/LICENSE
sdflexutils-1.5.1.dist-info/METADATA
sdflexutils-1.5.1.dist-info/WHEEL
sdflexutils-1.5.1.dist-info/entry_points.txt
sdflexutils-1.5.1.dist-info/pbr.json
sdflexutils-1.5.1.dist-info/top_level.txt
sdflexutils-1.5.1.dist-info/RECORD
