Metadata-Version: 2.1
Name: sdflexutils
Version: 1.5.1
Summary: Client Library for interfacing with various devices in HPE Superdome Flex Servers.
Home-page: https://github.com/HewlettPackard/sdflexutils/wiki
Author: Hewlett Packard Enterprise
Author-email: sdflex.openstack@hpe.com
License: Apache License, Version 2.0
Classifier: Environment :: OpenStack
Classifier: Intended Audience :: Information Technology
Classifier: Intended Audience :: System Administrators
Classifier: License :: OSI Approved :: Apache Software License
Classifier: Operating System :: OS Independent
Classifier: Programming Language :: Python
Classifier: Programming Language :: Python :: 3
Classifier: Programming Language :: Python :: 3.5
Classifier: Programming Language :: Python :: 3.7
License-File: LICENSE
License-File: AUTHORS
Requires-Dist: pbr (!=2.1.0,>=2.0.0)
Requires-Dist: six (>=1.9.0)
Requires-Dist: oslo.concurrency (>=4.2.0)
Requires-Dist: oslo.serialization (!=2.19.1,>=2.18.0)
Requires-Dist: oslo.utils (>=3.38.0)
Requires-Dist: jsonschema (>=3.2.0)
Requires-Dist: requests (>=2.14.2)
Requires-Dist: retrying (!=1.3.0,>=1.2.3)
Requires-Dist: sushy (<5.0.0,>=4.3.0)
